memmpy/__init__.py
memmpy/_index.py
memmpy/_jagged.py
memmpy/_labels.py
memmpy/_loader.py
memmpy/_shuffle.py
memmpy/_subset.py
memmpy/_vector.py
memmpy/reroot.py
memmpy-0.1.11.dist-info/METADATA
memmpy-0.1.11.dist-info/WHEEL
memmpy-0.1.11.dist-info/top_level.txt
memmpy-0.1.11.dist-info/RECORD
