Metadata-Version: 2.1
Name: memmpy
Version: 0.1.11
Summary: Memory mapped of datasets
Home-page: https://github.com/pwolle/memmpy
Author: Paul Wollenhaupt
Author-email: paul.wollenhaupt@gmail.com
Requires-Python: >=3.10
Requires-Dist: numpy
Requires-Dist: beartype
